volcengine_pkaclient/__init__.py
volcengine_pkaclient/pkaPka_wf.py
volcengine_qcclient/__init__.py
volcengine_qcclient/config.py
volcengine_qcclient/qc_batchjob.py
volcengine_qcclient/qc_client.py
volcengine_qcclient/qc_service.py
volcengine_qcclient/cli/__init__.py
volcengine_qcclient/cli/configure.py
volcengine_qcclient/cli/job.py
volcengine_qcclient/cli/main.py
volcengine_qcclient/cli/service.py
volcengine_qcclient/cli/task.py
volcengine_qcclient/cli/utils.py
volcengine_qcclient/drivers/__init__.py
volcengine_qcclient/drivers/eda_validation.py
volcengine_qcclient/drivers/elements.py
volcengine_qcclient/drivers/opt_validation.py
volcengine_qcclient/drivers/pygsm_validation.py
volcengine_qcclient/drivers/sp_validation.py
volcengine_qcclient/pyscf/__init__.py
volcengine_qcclient/pyscf/_future.py
volcengine_qcclient/pyscf/df/__init__.py
volcengine_qcclient/pyscf/dft/__init__.py
volcengine_qcclient/pyscf/dft/rks.py
volcengine_qcclient/pyscf/dft/uks.py
volcengine_qcclient/pyscf/grad/__init__.py
volcengine_qcclient/pyscf/grad/rhf.py
volcengine_qcclient/pyscf/grad/rks.py
volcengine_qcclient/pyscf/grad/uhf.py
volcengine_qcclient/pyscf/grad/uks.py
volcengine_qcclient/pyscf/gto/__init__.py
volcengine_qcclient/pyscf/gto/mole.py
volcengine_qcclient/pyscf/hessian/__init__.py
volcengine_qcclient/pyscf/hessian/rhf.py
volcengine_qcclient/pyscf/hessian/rks.py
volcengine_qcclient/pyscf/hessian/uhf.py
volcengine_qcclient/pyscf/hessian/uks.py
volcengine_qcclient/pyscf/scf/__init__.py
volcengine_qcclient/pyscf/scf/hf.py
volcengine_qcclient/pyscf/scf/uhf.py
volcengine_qcclient/pyscf/solvent/__init__.py
volcengine_qcclient/pyscf/solvent/pcm.py
volcengine_qcclient/pyscf/solvent/smd.py
volcengine_qcclient/pyscf/soscf/__init__.py
volcengine_qcclient/pyscf/tdscf/__init__.py
volcengine_qcclient/pyscf/tdscf/rhf.py
volcengine_qcclient/pyscf/tdscf/rks.py
volcengine_qcclient/pyscf/tdscf/uhf.py
volcengine_qcclient/pyscf/tdscf/uks.py
volcengine_qcclient/pyscf/x2c/__init__.py
volcengine_qcclient-0.1.22.dist-info/METADATA
volcengine_qcclient-0.1.22.dist-info/WHEEL
volcengine_qcclient-0.1.22.dist-info/entry_points.txt
volcengine_qcclient-0.1.22.dist-info/top_level.txt
volcengine_qcclient-0.1.22.dist-info/RECORD
