Metadata-Version: 2.1
Name: volcengine-qcclient
Version: 0.1.22
Summary: A Python client for volcengine quantum chemistry service.
Home-page: https://github.com/yourusername/myclient
Author: Lifei Chen
Author-email: chenlifei.fly@bytedance.com
License: MIT
Classifier: Programming Language :: Python :: 3
Classifier: License :: OSI Approved :: MIT License
Classifier: Operating System :: OS Independent
Requires-Python: >=3.6
Requires-Dist: requests (>=2.20.0)
Requires-Dist: volcengine (>=1.0.161)
Requires-Dist: retry (>=0.9.2)
Requires-Dist: typing-extensions (>=4.7.0)
Requires-Dist: h5py (>=3.0.0)
Requires-Dist: pandas
Requires-Dist: pyyaml
Requires-Dist: prettytable (>=3.0.0)
